flip_flops/d/d_async_rst/d_async_rst.v
module D (
  input wire clk,
  input wire rst_n,
  input wire d,
  output reg q
);
  always @(posedge clk or negedge rst_n) begin
    if(!rst_n)
      q <= 0;
    else
      q <= d;
  end
endmodule

flip_flops/d/d_async_rst/d_async_rst_tb.v
module D_TB;
  reg clk;
  reg rst_n;
  reg d;
  wire q;

  D uut (
    .clk(clk),
    .rst_n(rst_n),
    .d(d),
    .q(q)
  );

  always #5 clk = ~clk;

  initial begin
    $dumpfile("d.vcd");
    $dumpvars(0, D_TB);
    clk = 0;
    rst_n = 0;
    d = 0;
    #10;
    
    rst_n = 1;
    #10;

    d = 1; #10;
    d = 0; #10;
    d = 1; #10;

    rst_n = 0; #10;
    rst_n = 1; #10;

    d = 0; #10;
    d = 1; #10;

    $finish;
  end
endmodule

flip_flops/d/d_async_rst/d.vcd
$date
	Sat Mar 15 17:15:32 2025
$end
$version
	Icarus Verilog
$end
$timescale
	1s
$end
$scope module D_TB $end
$var wire 1 ! q $end
$var reg 1 " clk $end
$var reg 1 # d $end
$var reg 1 $ rst_n $end
$scope module uut $end
$var wire 1 " clk $end
$var wire 1 # d $end
$var wire 1 $ rst_n $end
$var reg 1 ! q $end
$upscope $end
$upscope $end
$enddefinitions $end
#0
$dumpvars
0$
0#
0"
0!
$end
#5
1"
#10
0"
1$
#15
1"
#20
0"
1#
#25
1!
1"
#30
0"
0#
#35
0!
1"
#40
0"
1#
#45
1!
1"
#50
0!
0"
0$
#55
1"
#60
0"
1$
#65
1!
1"
#70
0"
0#
#75
0!
1"
#80
0"
1#
#85
1!
1"
