adders/full/full_adder.v
module FULL_ADDER(
  input a,
  input b,
  input cin,
  output sum,
  output cout
);
  wire and_res = a & b;
  wire xor_res = a ^ b;
  assign sum = xor_res ^ cin;
  assign cout = and_res | (xor_res & cin);
endmodule

adders/full/full_adder_tb.v
module FULL_ADDER_TB;
  reg a, b, cin;
  wire sum, cout;

  FULL_ADDER uut (
    .a(a),
    .b(b),
    .cin(cin),
    .sum(sum),
    .cout(cout)
  );

  initial begin
    $dumpfile("full_adder.vcd");
    $dumpvars(0, FULL_ADDER_TB);
    $monitor("A=%b, B=%b, CIN=%b | SUM=%b, COUT=%b", a, b, cin, sum, cout);
    a = 0; b = 0; cin = 0; #10;
    a = 0; b = 0; cin = 1; #10;
    a = 0; b = 1; cin = 0; #10;
    a = 0; b = 1; cin = 1; #10;
    a = 1; b = 0; cin = 0; #10;
    a = 1; b = 0; cin = 1; #10;
    a = 1; b = 1; cin = 0; #10;
    a = 1; b = 1; cin = 1; #10;
    $finish;
  end
endmodule

adders/full/full_adder.vcd
$date
	Fri Feb  7 13:05:35 2025
$end
$version
	Icarus Verilog
$end
$timescale
	1s
$end
$scope module FULL_ADDER_TB $end
$var wire 1 ! sum $end
$var wire 1 " cout $end
$var reg 1 # a $end
$var reg 1 $ b $end
$var reg 1 % cin $end
$scope module uut $end
$var wire 1 # a $end
$var wire 1 & and_res $end
$var wire 1 $ b $end
$var wire 1 % cin $end
$var wire 1 " cout $end
$var wire 1 ! sum $end
$var wire 1 ' xor_res $end
$upscope $end
$upscope $end
$enddefinitions $end
#0
$dumpvars
0'
0&
0%
0$
0#
0"
0!
$end
#10
1!
1%
#20
1'
0%
1$
#30
1"
0!
1%
#40
0"
1!
0%
0$
1#
#50
1"
0!
1%
#60
1&
0'
0%
1$
#70
1!
1%
