decoder/3to8/decoder3to8.v
module DECODER3TO8 (
  input wire a,
  input wire b,
  input wire c,
  output wire d0,
  output wire d1,
  output wire d2,
  output wire d3,
  output wire d4,
  output wire d5,
  output wire d6,
  output wire d7
);

  assign d0 = (~a & ~b & ~c);
  assign d1 = (~a & ~b &  c);
  assign d2 = (~a &  b & ~c);
  assign d3 = (~a &  b &  c);
  assign d4 = ( a & ~b & ~c);
  assign d5 = ( a & ~b &  c);
  assign d6 = ( a &  b & ~c);
  assign d7 = ( a &  b &  c);
endmodule

decoder/3to8/decoder3to8_tb.v
`timescale 1ns / 1ps

module DECODER3TO8_TB;
  reg a, b, c;
  wire d0, d1, d2, d3, d4, d5, d6, d7;

  DECODER3TO8 uut (
    .a(a),
    .b(b),
    .c(c),
    .d0(d0),
    .d1(d1),
    .d2(d2),
    .d3(d3),
    .d4(d4),
    .d5(d5),
    .d6(d6),
    .d7(d7)
  );

  initial begin
    $dumpfile("decoder3to8_tb.vcd");
    $dumpvars(0, DECODER3TO8_TB);
    {a, b, c} = 3'b000; #10;
    {a, b, c} = 3'b001; #10;
    {a, b, c} = 3'b010; #10;
    {a, b, c} = 3'b011; #10;
    {a, b, c} = 3'b100; #10;
    {a, b, c} = 3'b101; #10;
    {a, b, c} = 3'b110; #10;
    {a, b, c} = 3'b111; #10;
    $finish;
  end
  initial begin
    $monitor("Time = %0t | a = %b, b = %b, c = %b | d0=%b d1=%b d2=%b d3=%b d4=%b d5=%b d6=%b d7=%b", $time, a, b, c, d0, d1, d2, d3, d4, d5, d6, d7);
  end
endmodule

decoder/3to8/decoder3to8_tb.vcd
$date
	Sat Feb  8 19:04:43 2025
$end
$version
	Icarus Verilog
$end
$timescale
	1ps
$end
$scope module DECODER3TO8_TB $end
$var wire 1 ! d7 $end
$var wire 1 " d6 $end
$var wire 1 # d5 $end
$var wire 1 $ d4 $end
$var wire 1 % d3 $end
$var wire 1 & d2 $end
$var wire 1 ' d1 $end
$var wire 1 ( d0 $end
$var reg 1 ) a $end
$var reg 1 * b $end
$var reg 1 + c $end
$scope module uut $end
$var wire 1 ) a $end
$var wire 1 * b $end
$var wire 1 + c $end
$var wire 1 ( d0 $end
$var wire 1 ' d1 $end
$var wire 1 & d2 $end
$var wire 1 % d3 $end
$var wire 1 $ d4 $end
$var wire 1 # d5 $end
$var wire 1 " d6 $end
$var wire 1 ! d7 $end
$upscope $end
$upscope $end
$enddefinitions $end
#0
$dumpvars
0+
0*
0)
1(
0'
0&
0%
0$
0#
0"
0!
$end
#10000
0(
1'
1+
#20000
0(
1&
0'
1*
0+
#30000
0&
1%
1+
#40000
1$
0%
1)
0*
0+
#50000
0$
1#
1+
#60000
0$
1"
0#
1*
0+
#70000
0"
1!
1+
