flip_flops/d/d.v
module D (
  input wire d,
  input wire clk,
  input wire rst,
  output reg Q
);
  always @(posedge clk) begin
    if(rst)
      Q <= 0;
    else
      Q <= d;
  end
endmodule

flip_flops/d/d_tb.v
module Testbench;
  reg d, clk, rst;
  wire Q;

  D uut (.d(d), .clk(clk), .rst(rst), .Q(Q));

  always #5 clk = ~clk;
  initial begin
    $dumpfile("d.vcd");
    $dumpvars(0, Testbench);
    clk = 0; rst = 1; d = 0;
    #10 rst = 0; d = 1;
    #10 d = 0;
    #10 d = 1;
    #10 rst = 1; // Reset
    #10 rst = 0; d = 0;
    #10 d = 1;
    #20 $finish;
  end
endmodule

flip_flops/d/d.vcd
$date
	Mon Feb  3 22:17:34 2025
$end
$version
	Icarus Verilog
$end
$timescale
	1s
$end
$scope module Testbench $end
$var wire 1 ! Q $end
$var reg 1 " clk $end
$var reg 1 # d $end
$var reg 1 $ rst $end
$scope module uut $end
$var wire 1 " clk $end
$var wire 1 # d $end
$var wire 1 $ rst $end
$var reg 1 ! Q $end
$upscope $end
$upscope $end
$enddefinitions $end
#0
$dumpvars
1$
0#
0"
x!
$end
#5
0!
1"
#10
0"
1#
0$
#15
1!
1"
#20
0"
0#
#25
0!
1"
#30
0"
1#
#35
1!
1"
#40
0"
1$
#45
0!
1"
#50
0"
0#
0$
#55
1"
#60
0"
1#
#65
1!
1"
