alu/16bit/alu.v
module ALU (
  input [15:0] X,
  input [15:0] Y,
  input [2:0] sel,
  output reg [15:0] alu_out,
  output reg carry_out, borrow_out
);
always @(*) begin
  carry_out = 0;
  borrow_out = 0;
  case (sel)
    3'b000: {carry_out, alu_out} = X + Y;
    3'b001: begin
      alu_out = X - Y;
      borrow_out = (X < Y) ? 1 : 0;
    end
    3'b010: alu_out = X & Y;
    3'b011: alu_out = X | Y;
    3'b100: alu_out = X ^ Y;
    3'b101: alu_out = ~X;
    3'b110: alu_out = X << 1;
    3'b111: alu_out = X >> 1;
    default: alu_out = 16'b0;
  endcase
end
endmodule

alu/16bit/alu_tb.v
module ALU_TB;
  reg [15:0] X, Y;
  reg [2:0] sel;
  wire [15:0] alu_out;
  wire carry_out;
  wire borrow_out;

  // Instantiate the ALU module
  ALU uut (
    .X(X),
    .Y(Y),
    .sel(sel),
    .alu_out(alu_out),
    .carry_out(carry_out),
    .borrow_out(borrow_out)
  );
  
  initial begin
    $dumpfile("alu.vcd");  // For waveform analysis
    $dumpvars(0, ALU_TB);

    // Test Case 1: Addition without carry
    X = 16'h0001; Y = 16'h0001; sel = 3'b000; #10;
    $display("ADD: X=%h, Y=%h, sel=%b, alu_out=%h, carry_out=%b, borrow_out=%b", X, Y, sel, alu_out, carry_out, borrow_out);

    // Test Case 2: Addition with carry (overflow case)
    X = 16'hFFFF; Y = 16'h0001; sel = 3'b000; #10;
    $display("ADD OVERFLOW: X=%h, Y=%h, sel=%b, alu_out=%h, carry_out=%b, borrow_out=%b", X, Y, sel, alu_out, carry_out, borrow_out);

    // Test Case 3: Subtraction without borrow
    X = 16'h0005; Y = 16'h0002; sel = 3'b001; #10;
    $display("SUB: X=%h, Y=%h, sel=%b, alu_out=%h, borrow_out=%b", X, Y, sel, alu_out, borrow_out);

    // Test Case 4: Subtraction with borrow (X < Y)
    X = 16'h0001; Y = 16'h0002; sel = 3'b001; #10;
    $display("SUB (WITH BORROW): X=%h, Y=%h, sel=%b, alu_out=%h, borrow_out=%b", X, Y, sel, alu_out, borrow_out);

    // Test Case 5: Bitwise AND
    X = 16'h0F0F; Y = 16'hF0F0; sel = 3'b010; #10;
    $display("AND: X=%h, Y=%h, sel=%b, alu_out=%h", X, Y, sel, alu_out);

    // Test Case 6: Bitwise OR
    X = 16'h0F0F; Y = 16'hF0F0; sel = 3'b011; #10;
    $display("OR: X=%h, Y=%h, sel=%b, alu_out=%h", X, Y, sel, alu_out);

    // Test Case 7: Bitwise XOR
    X = 16'hAAAA; Y = 16'h5555; sel = 3'b100; #10;
    $display("XOR: X=%h, Y=%h, sel=%b, alu_out=%h", X, Y, sel, alu_out);

    // Test Case 8: Bitwise NOT (Y is ignored)
    X = 16'h1234; sel = 3'b101; #10;
    $display("NOT: X=%h, sel=%b, alu_out=%h", X, sel, alu_out);

    // Test Case 9: Left Shift
    X = 16'h0001; sel = 3'b110; #10;
    $display("LSHIFT: X=%h, sel=%b, alu_out=%h", X, sel, alu_out);

    // Test Case 10: Right Shift
    X = 16'h8000; sel = 3'b111; #10;
    $display("RSHIFT: X=%h, sel=%b, alu_out=%h", X, sel, alu_out);

    $finish;
  end
endmodule

alu/16bit/alu.vcd
$date
	Fri Feb 14 01:53:58 2025
$end
$version
	Icarus Verilog
$end
$timescale
	1s
$end
$scope module ALU_TB $end
$var wire 1 ! carry_out $end
$var wire 1 " borrow_out $end
$var wire 16 # alu_out [15:0] $end
$var reg 16 $ X [15:0] $end
$var reg 16 % Y [15:0] $end
$var reg 3 & sel [2:0] $end
$scope module uut $end
$var wire 16 ' X [15:0] $end
$var wire 16 ( Y [15:0] $end
$var wire 3 ) sel [2:0] $end
$var reg 16 * alu_out [15:0] $end
$var reg 1 " borrow_out $end
$var reg 1 ! carry_out $end
$upscope $end
$upscope $end
$enddefinitions $end
#0
$dumpvars
b10 *
b0 )
b1 (
b1 '
b0 &
b1 %
b1 $
b10 #
0"
0!
$end
#10
1!
b0 #
b0 *
b1111111111111111 $
b1111111111111111 '
#20
b11 #
b11 *
0!
b1 &
b1 )
b10 %
b10 (
b101 $
b101 '
#30
1"
b1111111111111111 #
b1111111111111111 *
b1 $
b1 '
#40
b0 #
b0 *
0"
b10 &
b10 )
b1111000011110000 %
b1111000011110000 (
b111100001111 $
b111100001111 '
#50
b1111111111111111 #
b1111111111111111 *
b11 &
b11 )
#60
b100 &
b100 )
b101010101010101 %
b101010101010101 (
b1010101010101010 $
b1010101010101010 '
#70
b1110110111001011 #
b1110110111001011 *
b101 &
b101 )
b1001000110100 $
b1001000110100 '
#80
b10 #
b10 *
b110 &
b110 )
b1 $
b1 '
#90
b100000000000000 #
b100000000000000 *
b111 &
b111 )
b1000000000000000 $
b1000000000000000 '
