flip_flops/sr/sr.v
module SR (
  input wire S,
  input wire R,
  input wire CLK,
  output reg Q,
  output reg Qn
);
  initial begin
    Q = 1'b0;
    Qn = 1'b0;
  end

  always @(posedge CLK) begin
    if (S & R) begin
      Q <= 1'bx;
      Qn <= 1'bx;
    end
    else if (S) begin
      Q <= 1'b1;
      Qn <= 1'b0;
    end
    else if (R) begin
      Q <= 1'b0;
      Qn <= 1'b1;
    end
  end
endmodule

flip_flops/sr/sr_tb.v
`timescale 1ns/1ps
module Testbench;
  reg S, R, CLK;
  wire Q, Qn;

  SR uut (
    .S(S),
    .R(R),
    .CLK(CLK),
    .Q(Q),
    .Qn(Qn)
  );

  always #5 CLK = ~CLK;

  initial begin
    CLK = 0;
    S = 0;
    R = 0;

    $dumpfile("sr.vcd");
    $dumpvars(0, Testbench);

    #10 S = 1; R = 0;
    #10 S = 0; R = 1;
    #10 S = 1; R = 1;
    #10 S = 0; R = 0;
    #10 S = 1; R = 0;
    #10 S = 0; R = 1;
    #10 S = 1; R = 1;
    #10 $finish;
  end
  initial begin
    $monitor("Time=%0t | S=%b | R=%b | CLK=%b | Q=%b | Qn=%b", $time, S, R, CLK, Q, Qn);
  end
endmodule

flip_flops/sr/sr.vcd
$date
	Mon Feb  3 14:37:04 2025
$end
$version
	Icarus Verilog
$end
$timescale
	1ps
$end
$scope module Testbench $end
$var wire 1 ! Qn $end
$var wire 1 " Q $end
$var reg 1 # CLK $end
$var reg 1 $ R $end
$var reg 1 % S $end
$scope module uut $end
$var wire 1 # CLK $end
$var wire 1 $ R $end
$var wire 1 % S $end
$var reg 1 " Q $end
$var reg 1 ! Qn $end
$upscope $end
$upscope $end
$enddefinitions $end
#0
$dumpvars
0%
0$
0#
0"
0!
$end
#5000
1#
#10000
0#
1%
#15000
1"
1#
#20000
0#
1$
0%
#25000
1!
0"
1#
#30000
0#
1%
#35000
x!
x"
1#
#40000
0#
0$
0%
#45000
1#
#50000
0#
1%
#55000
0!
1"
1#
#60000
0#
1$
0%
#65000
1!
0"
1#
#70000
0#
1%
#75000
x!
x"
1#
