fsm/dfa/ends_with_0/ends_0.v
// Deterministic Finite Automaton (DFA)
// Accepts binary string that ends with the 0

module ENDS_WITH_0(
  input clk,              // clock signal
  input rst,              // reset signal
  input in,               // input binary bit
  output reg accept       // output signal indicating if string ends with 0 or not!
);
  parameter S0 = 1'b0, S1 = 1'b1;
  reg state, next_state;

  always @(posedge clk or posedge rst) begin
    if (rst) state <= S0;
    else state <= next_state;
  end

  always @(*) begin
    case (state)
      S0: next_state = (in == 0) ? S0 : S1;
      S1: next_state = (in == 0) ? S0 : S1;
      default: next_state = S0;
    endcase
  end

  always @(*) begin
    accept = (state == S0);
  end
endmodule

fsm/dfa/ends_with_0/ends_0_tb.v
module ENDS_WITH_0_TB;
  reg clk, rst, in;
  wire accept;

  ENDS_WITH_0 uut (
    .clk(clk),
    .rst(rst),
    .in(in),
    .accept(accept)
  );

  always #5 clk = ~clk;

  initial begin
    clk = 0;
    rst = 1;
    in = 0;
    #10;

    rst = 0;
    #10;

    // sequence 1100 should be accepted
    in = 1; #10;
    in = 1; #10;
    in = 0; #10;
    in = 0; #10;

    // sequence 1011 shouldn't be accepted
    in = 1; #10;
    in = 0; #10;
    in = 1; #10;
    in = 1; #10;

    // sequence 100 should be accepted
    in = 1; #10;
    in = 0; #10;
    in = 0; #10;

    // sequence 11 shouldn't be accepted
    in = 1; #10;
    in = 1; #10;
    $finish;
  end

  initial begin
    $dumpfile("ends_0.vcd");
    $dumpvars(0, ENDS_WITH_0_TB);
  end
endmodule

fsm/dfa/ends_with_0/ends_0.vcd
$date
	Thu Feb  6 00:17:00 2025
$end
$version
	Icarus Verilog
$end
$timescale
	1s
$end
$scope module ENDS_WITH_0_TB $end
$var wire 1 ! accept $end
$var reg 1 " clk $end
$var reg 1 # in $end
$var reg 1 $ rst $end
$scope module uut $end
$var wire 1 " clk $end
$var wire 1 # in $end
$var wire 1 $ rst $end
$var reg 1 ! accept $end
$var reg 1 % next_state $end
$var reg 1 & state $end
$upscope $end
$upscope $end
$enddefinitions $end
#0
$dumpvars
0&
0%
1$
0#
0"
1!
$end
#5
1"
#10
0"
0$
#15
1"
#20
1%
0"
1#
#25
0!
1&
1"
#30
0"
#35
1"
#40
0%
0"
0#
#45
1!
0&
1"
#50
0"
#55
1"
#60
1%
0"
1#
#65
0!
1&
1"
#70
0%
0"
0#
#75
1!
0&
1"
#80
1%
0"
1#
#85
0!
1&
1"
#90
0"
#95
1"
#100
0"
#105
1"
#110
0%
0"
0#
#115
1!
0&
1"
#120
0"
#125
1"
#130
1%
0"
1#
#135
0!
1&
1"
