meta_state/meta.v
module meta (
  input wire clk_fast,
  input wire clk_slow,
  input wire rst,
  input wire async_signal,
  output reg stable_signal
);

  reg meta_ff;
  reg sync_ff;

  reg fast_signal;
  always @(posedge clk_fast or posedge rst) begin
    if (rst)
      fast_signal <= 0;
    else
      fast_signal <= async_signal;
  end

  always @(posedge clk_slow or posedge rst) begin
    if (rst) begin
      meta_ff  <= 0;
      sync_ff  <= 0;
      stable_signal <= 0;
    end else begin
      meta_ff  <= fast_signal;
      sync_ff  <= meta_ff;
      stable_signal <= sync_ff;
    end
  end
endmodule

meta_state/meta_tb.v
module meta_tb;
  reg clk_fast, clk_slow, rst, async_signal;
  wire stable_signal;

  meta uut (
    .clk_fast(clk_fast),
    .clk_slow(clk_slow),
    .rst(rst),
    .async_signal(async_signal),
    .stable_signal(stable_signal)
  );

  always #5 clk_fast = ~clk_fast;
  always #20 clk_slow = ~clk_slow;

  initial begin
    clk_fast = 0;
    clk_slow = 0;
    rst = 1;
    async_signal = 0;

    #50 rst = 0;

    #55 async_signal = 1;
    #37 async_signal = 0;
    #82 async_signal = 1;
    #23 async_signal = 0;
    #60 async_signal = 1;
    #15 async_signal = 0;

    #500 $finish;
  end

  initial begin
    $dumpfile("meta.vcd");
    $dumpvars(0, meta_tb);
  end
endmodule

meta_state/meta.vcd
$date
	Sat Jun 28 22:10:25 2025
$end
$version
	Icarus Verilog
$end
$timescale
	1s
$end
$scope module meta_tb $end
$var wire 1 ! stable_signal $end
$var reg 1 " async_signal $end
$var reg 1 # clk_fast $end
$var reg 1 $ clk_slow $end
$var reg 1 % rst $end
$scope module uut $end
$var wire 1 " async_signal $end
$var wire 1 # clk_fast $end
$var wire 1 $ clk_slow $end
$var wire 1 % rst $end
$var reg 1 & fast_signal $end
$var reg 1 ' meta_ff $end
$var reg 1 ! stable_signal $end
$var reg 1 ( sync_ff $end
$upscope $end
$upscope $end
$enddefinitions $end
#0
$dumpvars
0(
0'
0&
1%
0$
0#
0"
0!
$end
#5
1#
#10
0#
#15
1#
#20
0#
1$
#25
1#
#30
0#
#35
1#
#40
0#
0$
#45
1#
#50
0#
0%
#55
1#
#60
0#
1$
#65
1#
#70
0#
#75
1#
#80
0#
0$
#85
1#
#90
0#
#95
1#
#100
0#
1$
#105
1&
1#
1"
#110
0#
#115
1#
#120
0#
0$
#125
1#
#130
0#
#135
1#
#140
1'
0#
1$
#142
0"
#145
0&
1#
#150
0#
#155
1#
#160
0#
0$
#165
1#
#170
0#
#175
1#
#180
1(
0'
0#
1$
#185
1#
#190
0#
#195
1#
#200
0#
0$
#205
1#
#210
0#
#215
1#
#220
1!
0(
0#
1$
#224
1"
#225
1&
1#
#230
0#
#235
1#
#240
0#
0$
#245
1#
#247
0"
#250
0#
#255
0&
1#
#260
0!
0#
1$
#265
1#
#270
0#
#275
1#
#280
0#
0$
#285
1#
#290
0#
#295
1#
#300
0#
1$
#305
1#
#307
1"
#310
0#
#315
1&
1#
#320
0#
0$
#322
0"
#325
0&
1#
