shift_reg/siso/siso.v
module SISO #(
  parameter WIDTH = 4
)(
  input wire clk,
  input wire rst,
  input wire din,
  output wire dout
);
  reg [3:0] shift_reg;
  always @(posedge clk) begin
    if(rst) shift_reg <= 0;
    else shift_reg <= {shift_reg[2:0], din};
  end
  assign dout = shift_reg[3];
endmodule

shift_reg/siso/testbench.v
module Testbench;
  reg clk;
  reg din;
  wire dout;

  SISO uut(
    .clk(clk),
    .din(din),
    .dout(dout)
  );

  always #5 clk = ~clk;

  initial begin
    clk = 0;
    din = 0;

    #10 din = 1;
    #10 din = 0;
    #10 din = 1;
    #10 din = 1;
    #10 din = 0;
    #10 din = 0;
    #10 din = 1;
    #10 din = 1;
    #50 $finish;
  end

  initial begin
    $dumpfile("siso.vcd");
    $dumpvars(0, Testbench);
  end
endmodule

shift_reg/siso/siso.vcd
$date
	Sat Jun 28 22:27:39 2025
$end
$version
	Icarus Verilog
$end
$timescale
	1s
$end
$scope module Testbench $end
$var wire 1 ! dout $end
$var reg 1 " clk $end
$var reg 1 # din $end
$scope module uut $end
$var wire 1 " clk $end
$var wire 1 # din $end
$var wire 1 $ rst $end
$var wire 1 ! dout $end
$var reg 4 % shift_reg [3:0] $end
$upscope $end
$upscope $end
$enddefinitions $end
#0
$dumpvars
bx %
z$
0#
0"
x!
$end
#5
bx0 %
1"
#10
0"
1#
#15
bx01 %
1"
#20
0"
0#
#25
bx010 %
1"
#30
0"
1#
#35
0!
b101 %
1"
#40
0"
#45
1!
b1011 %
1"
#50
0"
0#
#55
0!
b110 %
1"
#60
0"
#65
1!
b1100 %
1"
#70
0"
1#
#75
b1001 %
1"
#80
0"
#85
0!
b11 %
1"
#90
0"
#95
b111 %
1"
#100
0"
#105
1!
b1111 %
1"
