fsm/dfa/det_1011/det_1011.v
module det_1011 (
  input wire clk,
  input wire reset,
  input wire in_bit,
  output reg detected
);

  parameter S0 = 3'b000,
            S1 = 3'b001,
            S2 = 3'b010,
            S3 = 3'b011,
            S4 = 3'b111;
  reg [2:0] current_state, next_state;

  always @(*) begin
    case (current_state)
      S0: next_state = (in_bit) ? S1 : S0;
      S1: next_state = (in_bit) ? S1 : S2;
      S2: next_state = (in_bit) ? S3 : S0;
      S3: next_state = (in_bit) ? S4 : S2;
      S4: next_state = (in_bit) ? S1 : S2;
      default: next_state = S0;
    endcase
  end

  always @(posedge clk or posedge reset) begin
    if (reset) current_state <= S0;
    else current_state <= next_state;
  end

  always @(posedge clk or posedge reset) begin
    if (reset) detected <= 0;
    else detected <= (next_state == S4);
  end
endmodule

fsm/dfa/det_1011/det_1011_tb.v
module det_1011_tb;
  reg clk, reset, in_bit;
  wire detected;

  det_1011 uut (
    .clk(clk),
    .reset(reset),
    .in_bit(in_bit),
    .detected(detected)
  );

  always #5 clk = ~clk;

  initial begin
    $dumpfile("det_1011.vcd");
    $dumpvars(0, det_1011_tb);
    $monitor("Time: %0t | in_bit: %b | detected: %b", $time, in_bit, detected);

    clk = 0;
    reset = 1;
    in_bit = 0;

    #10 reset = 0;
    #10 in_bit = 1;
    #10 in_bit = 0;
    #10 in_bit = 1;
    #10 in_bit = 1;
    #10 in_bit = 0;

    #10 in_bit = 1;
    #10 in_bit = 0;
    #10 in_bit = 1;
    #10 in_bit = 1;
    #10 in_bit = 1;
    #10 in_bit = 0;
    #10 in_bit = 1;
    #10 in_bit = 1;

    #20 $finish;
  end
endmodule

fsm/dfa/det_1011/det_1011.vcd
$date
	Sat Feb 15 01:57:57 2025
$end
$version
	Icarus Verilog
$end
$timescale
	1s
$end
$scope module det_1011_tb $end
$var wire 1 ! detected $end
$var reg 1 " clk $end
$var reg 1 # in_bit $end
$var reg 1 $ reset $end
$scope module uut $end
$var wire 1 " clk $end
$var wire 1 # in_bit $end
$var wire 1 $ reset $end
$var reg 3 % current_state [2:0] $end
$var reg 1 ! detected $end
$var reg 3 & next_state [2:0] $end
$upscope $end
$upscope $end
$enddefinitions $end
#0
$dumpvars
b0 &
b0 %
1$
0#
0"
0!
$end
#5
1"
#10
0"
0$
#15
1"
#20
b1 &
0"
1#
#25
b1 %
1"
#30
b10 &
0"
0#
#35
b0 &
b10 %
1"
#40
b11 &
0"
1#
#45
b111 &
b11 %
1"
#50
0"
#55
b1 &
b111 %
1!
1"
#60
b10 &
0"
0#
#65
b0 &
0!
b10 %
1"
#70
b11 &
0"
1#
#75
b111 &
b11 %
1"
#80
b10 &
0"
0#
#85
b0 &
b10 %
1"
#90
b11 &
0"
1#
#95
b111 &
b11 %
1"
#100
0"
#105
b1 &
1!
b111 %
1"
#110
0"
#115
b1 %
0!
1"
#120
b10 &
0"
0#
#125
b0 &
b10 %
1"
#130
b11 &
0"
1#
#135
b111 &
b11 %
1"
#140
0"
#145
b1 &
1!
b111 %
1"
#150
0"
#155
b1 %
0!
1"
