flip_flops/jk/jk.v
module JK (
  input CLK, J, K,
  output reg Q,
  output Qbar
);
  always @(posedge CLK) begin
    case ({J, K})
      2'b00: Q <= Q;
      2'b01: Q <= 0;
      2'b10: Q <= 1;
      2'b11: Q <= ~Q;
    endcase
  end
  assign Qbar = ~Q;
endmodule

flip_flops/jk/jk_tb.v
module JK_TB;
  reg CLK, J, K;
  wire Q, Qbar;

  JK uut (.CLK(CLK), .J(J), .K(K), .Q(Q), .Qbar(Qbar));

  initial begin
    CLK = 0; J = 0; K = 0; #10;
    J = 1; K = 0; #10;
    J = 0; K = 0; #10;
    J = 1; K = 1; #10;
    J = 1; K = 1; #10;
    J = 0; K = 0; #10;
    $finish;
  end

  always  #5 CLK = ~CLK;

  initial begin
    $dumpfile("jk.vcd");
    $dumpvars(0, JK_TB);
  end
endmodule

flip_flops/jk/jk.vcd
$date
	Sat Feb 15 01:02:47 2025
$end
$version
	Icarus Verilog
$end
$timescale
	1s
$end
$scope module JK_TB $end
$var wire 1 ! Qbar $end
$var wire 1 " Q $end
$var reg 1 # CLK $end
$var reg 1 $ J $end
$var reg 1 % K $end
$scope module uut $end
$var wire 1 # CLK $end
$var wire 1 $ J $end
$var wire 1 % K $end
$var wire 1 ! Qbar $end
$var reg 1 " Q $end
$upscope $end
$upscope $end
$enddefinitions $end
#0
$dumpvars
0%
0$
0#
x"
x!
$end
#5
1#
#10
0#
1$
#15
0!
1"
1#
#20
0#
0$
#25
1#
#30
0#
1%
1$
#35
1!
0"
1#
#40
0#
#45
0!
1"
1#
#50
0#
0%
0$
